odoo/addons/shopinvader_partner_firstname/README.rst
odoo/addons/shopinvader_partner_firstname/__init__.py
odoo/addons/shopinvader_partner_firstname/__manifest__.py
odoo/addons/shopinvader_partner_firstname/i18n/shopinvader_partner_firstname.pot
odoo/addons/shopinvader_partner_firstname/readme/CONTRIBUTORS.rst
odoo/addons/shopinvader_partner_firstname/readme/CREDITS.rst
odoo/addons/shopinvader_partner_firstname/readme/DESCRIPTION.rst
odoo/addons/shopinvader_partner_firstname/readme/USAGE.rst
odoo/addons/shopinvader_partner_firstname/services/__init__.py
odoo/addons/shopinvader_partner_firstname/services/customer.py
odoo/addons/shopinvader_partner_firstname/static/description/index.html
odoo/addons/shopinvader_partner_firstname/tests/__init__.py
odoo/addons/shopinvader_partner_firstname/tests/test_firstname.py
odoo13_addon_shopinvader_partner_firstname-13.0.1.0.1.dev3.dist-info/METADATA
odoo13_addon_shopinvader_partner_firstname-13.0.1.0.1.dev3.dist-info/WHEEL
odoo13_addon_shopinvader_partner_firstname-13.0.1.0.1.dev3.dist-info/top_level.txt
odoo13_addon_shopinvader_partner_firstname-13.0.1.0.1.dev3.dist-info/RECORD
