Metadata-Version: 2.1
Name: odoo13-addon-shopinvader_partner_firstname
Version: 13.0.1.0.1.dev3
Summary: Shopinvader Customer firstname/lastname
Home-page: https://github.com/shopinvader/odoo-shopinvader
Author: Camptocamp SA
License: AGPL-3
Classifier: Programming Language :: Python
Classifier: Framework :: Odoo
Classifier: Framework :: Odoo :: 13.0
Classifier: License :: OSI Approved :: GNU Affero General Public License v3
Requires-Python: >=3.5
Requires-Dist: odoo13-addon-partner-firstname
Requires-Dist: odoo13-addon-shopinvader
Requires-Dist: odoo <13.1dev,>=13.0a
